README.md
setup.py
python_graphs/__init__.py
python_graphs/control_flow.py
python_graphs/control_flow_graphviz.py
python_graphs/control_flow_graphviz_test.py
python_graphs/control_flow_test.py
python_graphs/control_flow_test_components.py
python_graphs/control_flow_visualizer.py
python_graphs/cyclomatic_complexity.py
python_graphs/cyclomatic_complexity_test.py
python_graphs/data_flow.py
python_graphs/data_flow_test.py
python_graphs/instruction.py
python_graphs/instruction_test.py
python_graphs/program_graph.py
python_graphs/program_graph_dataclasses.py
python_graphs/program_graph_graphviz.py
python_graphs/program_graph_graphviz_test.py
python_graphs/program_graph_test.py
python_graphs/program_graph_test_components.py
python_graphs/program_graph_visualizer.py
python_graphs/program_utils.py
python_graphs.egg-info/PKG-INFO
python_graphs.egg-info/SOURCES.txt
python_graphs.egg-info/dependency_links.txt
python_graphs.egg-info/requires.txt
python_graphs.egg-info/top_level.txt