Metadata-Version: 1.1
Name: python-graphs
Version: 1.0.1
Summary: A library for generating graph representations of Python programs.
Home-page: https://github.com/google-research/python-graphs
Author: David Bieber
Author-email: dbieber@google.com
License: Apache Software License
Keywords: python program control flow data flow graph neural network
Platform: UNKNOWN
Classifier: Development Status :: 4 - Beta
Classifier: Intended Audience :: Developers
Classifier: Topic :: Software Development :: Libraries :: Python Modules
Classifier: License :: OSI Approved :: Apache Software License
Classifier: Programming Language :: Python
Classifier: Programming Language :: Python :: 3
Classifier: Programming Language :: Python :: 3.6
Classifier: Programming Language :: Python :: 3.7
Classifier: Programming Language :: Python :: 3.8
Classifier: Programming Language :: Python :: 3.9
Classifier: Operating System :: OS Independent
Classifier: Operating System :: POSIX
Classifier: Operating System :: MacOS
Classifier: Operating System :: Unix
